rich_click/__init__.py
rich_click/__main__.py
rich_click/_click_types_cache.py
rich_click/_compat_click.py
rich_click/_internal_types.py
rich_click/cli.py
rich_click/decorators.py
rich_click/decorators.pyi
rich_click/patch.py
rich_click/py.typed
rich_click/rich_box.py
rich_click/rich_click.py
rich_click/rich_click_theme.py
rich_click/rich_command.py
rich_click/rich_command.pyi
rich_click/rich_context.py
rich_click/rich_group.py
rich_click/rich_help_configuration.py
rich_click/rich_help_formatter.py
rich_click/rich_help_rendering.py
rich_click/rich_panel.py
rich_click/rich_parameter.py
rich_click/utils.py
rich_click-1.9.0.dist-info/licenses/LICENSE
rich_click-1.9.0.dist-info/METADATA
rich_click-1.9.0.dist-info/WHEEL
rich_click-1.9.0.dist-info/entry_points.txt
rich_click-1.9.0.dist-info/top_level.txt
rich_click-1.9.0.dist-info/RECORD
