Metadata-Version: 2.4
Name: rich-click
Version: 1.9.0
Summary: Format click help output nicely with rich
Author-email: Phil Ewels <phil@ewels.co.uk>
Maintainer-email: Phil Ewels <phil@ewels.co.uk>, Daniel Reeves <xdanielreeves@gmail.com>
License: MIT License
Project-URL: Documentation, https://github.com/ewels/rich-click
Project-URL: Homepage, https://github.com/ewels/rich-click
Project-URL: Issues, https://github.com/ewels/rich-click/issues
Project-URL: Repository, https://github.com/ewels/rich-click
Classifier: Development Status :: 3 - Alpha
Classifier: Intended Audience :: Developers
Classifier: Operating System :: OS Independent
Classifier: Programming Language :: Python
Classifier: Programming Language :: Python :: 3 :: Only
Classifier: Programming Language :: Python :: 3.8
Classifier: Programming Language :: Python :: 3.9
Classifier: Programming Language :: Python :: 3.10
Classifier: Programming Language :: Python :: 3.11
Classifier: Programming Language :: Python :: 3.12
Requires-Python: >=3.8
License-File: LICENSE
Requires-Dist: click>=8
Requires-Dist: rich>=12
Requires-Dist: typing-extensions>=4; python_version < "3.11"
Provides-Extra: dev
Requires-Dist: inline-snapshot>=0.24; extra == "dev"
Requires-Dist: jsonschema>=4; extra == "dev"
Requires-Dist: mypy>=1.14.1; extra == "dev"
Requires-Dist: nodeenv>=1.9.1; extra == "dev"
Requires-Dist: packaging>=25; extra == "dev"
Requires-Dist: pre-commit>=3.5; extra == "dev"
Requires-Dist: pytest>=8.3.5; extra == "dev"
Requires-Dist: pytest-cov>=5; extra == "dev"
Requires-Dist: rich-codex>=1.2.11; extra == "dev"
Requires-Dist: ruff>=0.12.4; extra == "dev"
Requires-Dist: typer>=0.15; extra == "dev"
Requires-Dist: types-setuptools>=75.8.0.20250110; extra == "dev"
Provides-Extra: docs
Requires-Dist: markdown-include>=0.8.1; extra == "docs"
Requires-Dist: mike>=2.1.3; extra == "docs"
Requires-Dist: mkdocs[docs]>=1.6.1; extra == "docs"
Requires-Dist: mkdocs-github-admonitions-plugin>=0.1.1; extra == "docs"
Requires-Dist: mkdocs-glightbox>=0.4; extra == "docs"
Requires-Dist: mkdocs-include-markdown-plugin>=7.1.7; python_version >= "3.9" and extra == "docs"
Requires-Dist: mkdocs-material[imaging]~=9.5.18; extra == "docs"
Requires-Dist: mkdocs-material-extensions>=1.3.1; extra == "docs"
Requires-Dist: mkdocs-redirects>=1.2.2; extra == "docs"
Requires-Dist: mkdocs-rss-plugin>=1.15; extra == "docs"
Requires-Dist: mkdocstrings[python]>=0.26.1; extra == "docs"
Requires-Dist: rich-codex>=1.2.11; extra == "docs"
Requires-Dist: typer>=0.15; extra == "docs"
Dynamic: license-file
